Metadata-Version: 2.4
Name: polytope_mars
Version: 0.3.7
Summary: High level meteorological feature extraction interface to Polytope
Home-page: https://github.com/ecmwf/polytope-mars
Author: ECMWF
Author-email: James.Hawkes@ecmwf.int, Adam.Warde@ecmwf.int, Mathilde.Leuridan@ecmwf.int
License-File: LICENSE
Requires-Dist: polytope-python
Requires-Dist: covjsonkit
Requires-Dist: xarray
Requires-Dist: shapely
Requires-Dist: geopandas
Requires-Dist: pyproj
Requires-Dist: geographiclib
Dynamic: author
Dynamic: author-email
Dynamic: home-page
Dynamic: license-file
Dynamic: requires-dist
Dynamic: summary
